my_project_poetry_1/__init__.py
my_project_poetry_1-0.1.0.dist-info/METADATA
my_project_poetry_1-0.1.0.dist-info/WHEEL
my_project_poetry_1-0.1.0.dist-info/RECORD
